chef_solo_cup/__init__.py
chef_solo_cup/helpers.py
chef_solo_cup/log.py
chef_solo_cup/parse_args.py
chef_solo_cup/version.py
chef_solo_cup/commands/__init__.py
chef_solo_cup/commands/bootstrap.py
chef_solo_cup/commands/chef.py
chef_solo_cup/commands/clean.py
chef_solo_cup/commands/default.py
chef_solo_cup/commands/gem.py
chef_solo_cup/commands/inspect.py
chef_solo_cup/commands/ruby.py
chef_solo_cup/commands/runner.py
chef_solo_cup/commands/sync.py
chef_solo_cup/commands/test.py
chef_solo_cup/commands/update.py
chef_solo_cup-0.3.0.data/scripts/chef-solo-cup
chef_solo_cup-0.3.0.dist-info/DESCRIPTION.rst
chef_solo_cup-0.3.0.dist-info/METADATA
chef_solo_cup-0.3.0.dist-info/metadata.json
chef_solo_cup-0.3.0.dist-info/pbr.json
chef_solo_cup-0.3.0.dist-info/RECORD
chef_solo_cup-0.3.0.dist-info/top_level.txt
chef_solo_cup-0.3.0.dist-info/WHEEL
