Metadata-Version: 2.0
Name: chef-solo-cup
Version: 0.3.0
Summary: Chef-Solo wrapper
Home-page: https://github.com/josegonzalez/chef-solo-cup
Author: Jose Diaz-Gonzalez
Author-email: email@josediazgonzalez.com
License: Copyright (c) 2014 Jose Diaz-Gonzalez
Requires-Dist: boto (==2.39.0)
Requires-Dist: dummymp (==0.5b2)
Requires-Dist: ecdsa (==0.13)
Requires-Dist: Fabric (==1.10.2)
Requires-Dist: paramiko (==1.16.0)
Requires-Dist: psutil (==3.4.2)
Requires-Dist: pycrypto (==2.6.1)
Requires-Dist: Unidecode (==0.4.18)
